[{"店舗名":"からやま 神奈川綾瀬店","住所":"〒252-1104 神奈川県綾瀬市大上４丁目２０−３１","ステータス":"APP_DISPLAY","region":"Ayase","lat":35.463444,"lng":139.430817},{"店舗名":"マムズキッチン","住所":"〒252-1104 神奈川県綾瀬市大上７丁目１１−１","ステータス":"APP_DISPLAY","region":"Ayase","lat":35.45961,"lng":139.433472},{"店舗名":"ヤトノクレープ","住所":"〒252-1106 神奈川県綾瀬市深谷南１丁目１０−２２","ステータス":"APP_DISPLAY","region":"Ayase","lat":35.428829,"lng":139.436844},{"店舗名":"焼肉あばら亭","住所":"〒252-1107 神奈川県綾瀬市深谷中","ステータス":"APP_DISPLAY","region":"Ayase","lat":35.434826,"lng":139.43074},{"店舗名":"コナズ珈琲 神奈川綾瀬店","住所":"〒252-1107 神奈川県綾瀬市深谷中１丁目４−３５","ステータス":"APP_DISPLAY","region":"Ayase","lat":35.43198,"lng":139.431015},{"店舗名":"吉野家 綾瀬市役所南通り店","住所":"〒252-1107 神奈川県綾瀬市深谷中４丁目６−１４","ステータス":"APP_DISPLAY","region":"Ayase","lat":35.439335,"lng":139.433105},{"店舗名":"EasyDay HALALRESTAURANT","住所":"〒252-1107 神奈川県綾瀬市深谷中７丁目１８−２","ステータス":"APP_DISPLAY","region":"Ayase","lat":35.436073,"lng":139.441605},{"店舗名":"リンガーハット 綾瀬市役所前店","住所":"〒252-1108 神奈川県綾瀬市深谷上１丁目１−５４","ステータス":"APP_DISPLAY","region":"Ayase","lat":35.437035,"lng":139.428223},{"店舗名":"ぎょうてん屋 綾瀬店","住所":"〒252-1108 神奈川県綾瀬市深谷上１丁目５−３","ステータス":"APP_DISPLAY","region":"Ayase","lat":35.439537,"lng":139.426407},{"店舗名":"Vietnam Restaurant LÊ KENTO","住所":"〒252-1108 神奈川県綾瀬市深谷上６丁目１６−３２","ステータス":"APP_DISPLAY","region":"Ayase","lat":35.439693,"lng":139.432968},{"店舗名":"丼＆唐揚げ ごはんどき 綾瀬上土棚店","住所":"〒252-1111 神奈川県綾瀬市上土棚北５丁目１０−２０","ステータス":"APP_DISPLAY","region":"Ayase","lat":35.419853,"lng":139.451859},{"店舗名":"まるよし亭","住所":"〒252-1113 神奈川県綾瀬市上土棚中２丁目１７−４１ ペパーミントハウス","ステータス":"APP_DISPLAY","region":"Ayase","lat":35.413857,"lng":139.450027},{"店舗名":"鰻の成瀬 神奈川綾瀬店","住所":"〒252-1121 神奈川県綾瀬市小園９２３−２","ステータス":"APP_DISPLAY","region":"Ayase","lat":35.452084,"lng":139.41658},{"店舗名":"CAFE KAKA","住所":"〒252-1125 神奈川県綾瀬市吉岡1206","ステータス":"RECEIPT","region":"Ayase","lat":35.426037,"lng":139.414459},{"店舗名":"ハラールカレー シャムス","住所":"〒252-1125 神奈川県綾瀬市吉岡東５丁目５－４１","ステータス":"APP_DISPLAY","region":"Ayase","lat":35.425358,"lng":139.429413},{"店舗名":"インドカレー パリカール","住所":"〒252-1132 神奈川県綾瀬市寺尾中１丁目８－１","ステータス":"APP_DISPLAY","region":"Ayase","lat":35.457893,"lng":139.426102},{"店舗名":"ピザハット 綾瀬寺尾本町店","住所":"〒252-1133 神奈川県綾瀬市寺尾本町１丁目２３−２３","ステータス":"APP_DISPLAY","region":"Ayase","lat":35.456135,"lng":139.421921},{"店舗名":"トスカーニパスタ 綾瀬寺尾本町店","住所":"〒252-1133 神奈川県綾瀬市寺尾本町１丁目２３−２３","ステータス":"APP_DISPLAY","region":"Ayase","lat":35.456135,"lng":139.421921},{"店舗名":"チキン・ウイングストリート 綾瀬寺尾本町店","住所":"〒252-1133 神奈川県綾瀬市寺尾本町１丁目２３−２３","ステータス":"APP_DISPLAY","region":"Ayase","lat":35.456135,"lng":139.421921},{"店舗名":"濃厚魚介豚骨つけ麺 つじ田","住所":"〒252-1135 神奈川県綾瀬市寺尾釜田２丁目１９","ステータス":"APP_DISPLAY","region":"Ayase","lat":35.448002,"lng":139.420929},{"店舗名":"デカ盛ダイニングおはな綾瀬店 DEKAMORI DINING OHANA AYASETEN","住所":"〒252-1135 神奈川県綾瀬市寺尾釜田２丁目１９−１","ステータス":"APP_DISPLAY","region":"Ayase","lat":35.44754,"lng":139.420944},{"店舗名":"濃厚魚介豚骨つけ麺 つじ田 綾瀬店","住所":"〒252-1135 神奈川県綾瀬市寺尾釜田２丁目１９−１","ステータス":"APP_DISPLAY","region":"Ayase","lat":35.44754,"lng":139.420944}]