[{"店舗名":"ロイヤルインドレストラン 福島店","住所":"〒960-0102","ステータス":"RECEIPT","region":"Fukushima","lat":37.795601,"lng":140.49678},{"店舗名":"ロマンドーロール ドン・キホーテ福島店","住所":"〒960-0102 福島県福島市鎌田字舟戸前14-1","ステータス":"RECEIPT","region":"Fukushima","lat":37.790348,"lng":140.488434},{"店舗名":"ROMANDÔ ROLLイオン福島店","住所":"〒960-0112 福島県福島市南矢野目西荒田","ステータス":"RECEIPT","region":"Fukushima","lat":37.788166,"lng":140.457825},{"店舗名":"ハッピーハッピーカレー（HAPPY HAPPY CURRY）","住所":"〒960-0113 福島県福島市北矢野目小原田西","ステータス":"RECEIPT","region":"Fukushima","lat":37.793934,"lng":140.461227},{"店舗名":"アジアンダイニングD 飯坂店","住所":"〒960-0201 福島県福島市飯坂町月崎町１２−４","ステータス":"RECEIPT","region":"Fukushima","lat":37.825584,"lng":140.446854},{"店舗名":"アジアンダイニングD 飯坂店","住所":"〒960-0201 福島県福島市飯坂町月崎町１２−４","ステータス":"RECEIPT","region":"Fukushima","lat":37.825584,"lng":140.446854},{"店舗名":"ピッツェリア　ラッポルティ","住所":"〒960-0241","ステータス":"RECEIPT","region":"Fukushima","lat":37.794506,"lng":140.427094},{"店舗名":"Blue Rose","住所":"〒960-0241 福島県福島市笹谷片目清水","ステータス":"RECEIPT","region":"Fukushima","lat":37.789852,"lng":140.445206},{"店舗名":"THE CURRY MASTER","住所":"〒960-1102 福島市永井川字壇ノ腰2-2","ステータス":"RECEIPT","region":"Fukushima","lat":37.723305,"lng":140.455872},{"店舗名":"インドネパール料理 アグラ本店 AGRA Main Store","住所":"〒960-8022 福島県福島市新浜町５−２７","ステータス":"RECEIPT","region":"Fukushima","lat":37.759727,"lng":140.470215},{"店舗名":"薄利多賣半兵ヱ　福島駅前店","住所":"〒960-8031 福島県福島市栄町","ステータス":"RECEIPT","region":"Fukushima","lat":37.754765,"lng":140.461639},{"店舗名":"麺家くさび 福島店","住所":"〒960-8031 福島県福島市栄町１１−２５","ステータス":"RECEIPT","region":"Fukushima","lat":37.75386,"lng":140.463394},{"店舗名":"一心亭福島分店","住所":"〒960-8032 福島県福島市陣場町７−１","ステータス":"RECEIPT","region":"Fukushima","lat":37.756256,"lng":140.462601},{"店舗名":"Daruma","住所":"〒960-8033","ステータス":"RECEIPT","region":"Fukushima","lat":37.757156,"lng":140.465149},{"店舗名":"夜＆韻 (ヨイン) yoin","住所":"〒960-8033 福島県福島市万世町１−３６ FSB V 1F","ステータス":"RECEIPT","region":"Fukushima","lat":37.756149,"lng":140.464294},{"店舗名":"アグラ2","住所":"〒960-8041 福島県福島市大町２−３５","ステータス":"RECEIPT","region":"Fukushima","lat":37.75415,"lng":140.466248},{"店舗名":"定食屋 やすまる","住所":"〒960-8043","ステータス":"RECEIPT","region":"Fukushima","lat":37.751076,"lng":140.464996},{"店舗名":"アグラMAX店","住所":"〒960-8051 福島県福島市曽根田町1-18","ステータス":"RECEIPT","region":"Fukushima","lat":37.758915,"lng":140.460648},{"店舗名":"ロマンドーロール ダイユーエイトMAX店","住所":"〒960-8051 福島県福島市曽根田町１−１８","ステータス":"RECEIPT","region":"Fukushima","lat":37.758915,"lng":140.460648},{"店舗名":"いとう寿司","住所":"〒960-8071 福島県福島市東中央１丁目１５−４","ステータス":"RECEIPT","region":"Fukushima","lat":37.761909,"lng":140.442001},{"店舗名":"デイブズダイナー Dave's Diner","住所":"〒960-8101 福島県福島市上町２","ステータス":"RECEIPT","region":"Fukushima","lat":37.754276,"lng":140.468399},{"店舗名":"焼き芋＆たこ焼き 〇勝 -マルショウ","住所":"〒960-8107 福島県福島市浜田町9-21","ステータス":"RECEIPT","region":"Fukushima","lat":37.75676,"lng":140.474335}]