[{"店舗名":"Ｎ白木屋 千里丘東口駅前店","住所":"〒166-0011 東京都杉並区梅里１丁目２１−１５ 牛久ハイツ","ステータス":"APP_DISPLAY","region":"Settsu","lat":35.69788,"lng":139.653488},{"店舗名":"ピッツェリア フィオーリ デル ソーレ","住所":"〒566-0001","ステータス":"APP_DISPLAY","region":"Settsu","lat":34.792835,"lng":135.551529},{"店舗名":"Danke","住所":"〒566-0001  大阪府摂津市千里丘１丁目１２−３２","ステータス":"APP_DISPLAY","region":"Settsu","lat":34.791561,"lng":135.548752},{"店舗名":"ほっかほっか亭 JR千里丘店","住所":"〒566-0001 大阪府摂津市千里丘１丁目１２−２９","ステータス":"APP_DISPLAY","region":"Settsu","lat":34.79174,"lng":135.549026},{"店舗名":"Vege Kitchen Awajin","住所":"〒566-0001 大阪府摂津市千里丘１丁目１２−３１","ステータス":"APP_DISPLAY","region":"Settsu","lat":34.791622,"lng":135.548843},{"店舗名":"ナンハウス","住所":"〒566-0001 大阪府摂津市千里丘１丁目１３−４","ステータス":"APP_DISPLAY","region":"Settsu","lat":34.792255,"lng":135.54924},{"店舗名":"k’s LATURA","住所":"〒566-0001 大阪府摂津市千里丘１丁目３−１１","ステータス":"APP_DISPLAY","region":"Settsu","lat":34.793209,"lng":135.551346},{"店舗名":"ケンタッキーフライドチキン 千里丘店","住所":"〒566-0001 大阪府摂津市千里丘２丁目１２−２８","ステータス":"APP_DISPLAY","region":"Settsu","lat":34.790672,"lng":135.547729},{"店舗名":"うどんと肉 角立 吹田店","住所":"〒566-0001 大阪府摂津市千里丘２丁目８−２１","ステータス":"APP_DISPLAY","region":"Settsu","lat":34.790001,"lng":135.546829},{"店舗名":"ハヤシ＆カレー ハッシュトマト 吹田店","住所":"〒566-0001 大阪府摂津市千里丘２丁目８−２１","ステータス":"APP_DISPLAY","region":"Settsu","lat":34.790001,"lng":135.546829},{"店舗名":"のり弁 浅草屋 吹田店","住所":"〒566-0001 大阪府摂津市千里丘２丁目８−２１","ステータス":"APP_DISPLAY","region":"Settsu","lat":34.790001,"lng":135.546829},{"店舗名":"どんぶり 神宮軒 吹田店","住所":"〒566-0001 大阪府摂津市千里丘２丁目８−２１","ステータス":"APP_DISPLAY","region":"Settsu","lat":34.790001,"lng":135.546829},{"店舗名":"かつ丼屋 のぶお 吹田店","住所":"〒566-0001 大阪府摂津市千里丘２丁目８−２１","ステータス":"APP_DISPLAY","region":"Settsu","lat":34.790001,"lng":135.546829},{"店舗名":"うなぎの照本 吹田店","住所":"〒566-0001 大阪府摂津市千里丘２丁目８−２１","ステータス":"APP_DISPLAY","region":"Settsu","lat":34.790001,"lng":135.546829},{"店舗名":"お粥 煮え花 吹田店","住所":"〒566-0001 大阪府摂津市千里丘２丁目８−２１","ステータス":"APP_DISPLAY","region":"Settsu","lat":34.790001,"lng":135.546829},{"店舗名":"ブラックビーフ 吹田店","住所":"〒566-0001 大阪府摂津市千里丘２丁目８−２１","ステータス":"APP_DISPLAY","region":"Settsu","lat":34.790001,"lng":135.546829},{"店舗名":"台湾カフェ 時香茶 吹田店","住所":"〒566-0001 大阪府摂津市千里丘２丁目８−２１","ステータス":"APP_DISPLAY","region":"Settsu","lat":34.790001,"lng":135.546829},{"店舗名":"韓国カルビ丼とスンドゥブ 洞山 吹田店","住所":"〒566-0001 大阪府摂津市千里丘２丁目８−２１","ステータス":"APP_DISPLAY","region":"Settsu","lat":34.790001,"lng":135.546829},{"店舗名":"鶏天豚天 通天道 吹田店","住所":"〒566-0001 大阪府摂津市千里丘２丁目８−２１","ステータス":"APP_DISPLAY","region":"Settsu","lat":34.790001,"lng":135.546829},{"店舗名":"仙台熟成牛たん たん助本家 吹田店","住所":"〒566-0001 大阪府摂津市千里丘２丁目８−２１","ステータス":"APP_DISPLAY","region":"Settsu","lat":34.790001,"lng":135.546829},{"店舗名":"焼きかつ丼 勝吉 吹田店","住所":"〒566-0001 大阪府摂津市千里丘２丁目８−２１","ステータス":"APP_DISPLAY","region":"Settsu","lat":34.790001,"lng":135.546829},{"店舗名":"旨辛スタミナ鉄板焼き 天神軒 吹田店","住所":"〒566-0001 大阪府摂津市千里丘２丁目８−２１","ステータス":"APP_DISPLAY","region":"Settsu","lat":34.790001,"lng":135.546829},{"店舗名":"十勝帯広豚丼 三代目ぶた広 吹田店","住所":"〒566-0001 大阪府摂津市千里丘２丁目８−２１","ステータス":"APP_DISPLAY","region":"Settsu","lat":34.790001,"lng":135.546829},{"店舗名":"熟成厚切りとんてき 三元道 吹田店","住所":"〒566-0001 大阪府摂津市千里丘２丁目８−２１","ステータス":"APP_DISPLAY","region":"Settsu","lat":34.790001,"lng":135.546829},{"店舗名":"出前つけ麺専門店 三田製麺所 吹田店","住所":"〒566-0001 大阪府摂津市千里丘２丁目８−２１","ステータス":"APP_DISPLAY","region":"Settsu","lat":34.790001,"lng":135.546829},{"店舗名":"出前家系ラーメン 吉祥寺 武蔵家 吹田店","住所":"〒566-0001 大阪府摂津市千里丘２丁目８−２１","ステータス":"APP_DISPLAY","region":"Settsu","lat":34.790001,"lng":135.546829},{"店舗名":"焼津 大坪水産のまぐろ丼 吹田店","住所":"〒566-0001 大阪府摂津市千里丘２丁目８−２１","ステータス":"APP_DISPLAY","region":"Settsu","lat":34.790001,"lng":135.546829},{"店舗名":"韓国クッパとビビンバ 全州 吹田店","住所":"〒566-0001 大阪府摂津市千里丘２丁目８−２１","ステータス":"APP_DISPLAY","region":"Settsu","lat":34.790001,"lng":135.546829},{"店舗名":"本格もつ鍋 竹名屋総本店 吹田店","住所":"〒566-0001 大阪府摂津市千里丘２丁目８−２１ マンション清涼","ステータス":"APP_DISPLAY","region":"Settsu","lat":34.790001,"lng":135.546829},{"店舗名":"宅配とんかつ かさねや 吹田店","住所":"〒566-0001 大阪府摂津市千里丘２丁目８−２１ マンション清涼","ステータス":"APP_DISPLAY","region":"Settsu","lat":34.790001,"lng":135.546829},{"店舗名":"元祖金沢チャンピオンカレーデリバリー 吹田店","住所":"〒566-0001 大阪府摂津市千里丘２丁目８−２１ マンション清涼 101","ステータス":"APP_DISPLAY","region":"Settsu","lat":34.790001,"lng":135.546829},{"店舗名":"ごはんや　八郷","住所":"〒566-0001 大阪府摂津市千里丘２丁目９−３３","ステータス":"APP_DISPLAY","region":"Settsu","lat":34.789433,"lng":135.548325},{"店舗名":"焼き屋エン","住所":"〒566-0001 大阪府摂津市千里丘４丁目１−１４","ステータス":"APP_DISPLAY","region":"Settsu","lat":34.786926,"lng":135.54808},{"店舗名":"はなまるうどん 摂津千里丘店","住所":"〒566-0001 大阪府摂津市千里丘５丁目４−１３","ステータス":"APP_DISPLAY","region":"Settsu","lat":34.787579,"lng":135.543152},{"店舗名":"スタミナ丼 活家 吹田店","住所":"〒566-0001 大阪府摂津市千里丘丁目８−２１","ステータス":"APP_DISPLAY","region":"Settsu","lat":34.792835,"lng":135.551529},{"店舗名":"からあげの鉄人 千里丘東口駅前店","住所":"〒566-0011 大阪府摂津市千里丘東１丁目１１−９ ナンノビル 地下 1階","ステータス":"APP_DISPLAY","region":"Settsu","lat":34.791508,"lng":135.551758},{"店舗名":"SHIROKI BURGER 千里丘東口駅前店","住所":"〒566-0011 大阪府摂津市千里丘東１丁目１１−９ ナンノ第１号館","ステータス":"APP_DISPLAY","region":"Settsu","lat":34.791508,"lng":135.551758},{"店舗名":"ハンバーグ TERU 千里丘東口駅前店","住所":"〒566-0011 大阪府摂津市千里丘東１丁目１１−９ ナンノ第１号館","ステータス":"APP_DISPLAY","region":"Settsu","lat":34.791508,"lng":135.551758},{"店舗名":"鉄板ステーキ 采、彩、","住所":"〒566-0022 大阪府摂津市三島３丁目１−３２","ステータス":"APP_DISPLAY","region":"Settsu","lat":34.78215,"lng":135.557953},{"店舗名":"パティスリー　キャトルフィユ","住所":"〒566-0023","ステータス":"APP_DISPLAY","region":"Settsu","lat":34.778713,"lng":135.550171},{"店舗名":"中国菜館 龍亀","住所":"〒566-0023 大阪府摂津市正雀３丁目１１−１０","ステータス":"APP_DISPLAY","region":"Settsu","lat":34.774849,"lng":135.551178},{"店舗名":"フォンテーヌヤマダ","住所":"〒566-0024","ステータス":"APP_DISPLAY","region":"Settsu","lat":34.776073,"lng":135.548248},{"店舗名":"寿し吉","住所":"〒566-0024","ステータス":"APP_DISPLAY","region":"Settsu","lat":34.776073,"lng":135.548248},{"店舗名":"【厳選マグロと秘伝の醤油】佐藤食品","住所":"〒566-0024 大阪府摂津市正雀本町１丁目１−３１","ステータス":"APP_DISPLAY","region":"Settsu","lat":34.775806,"lng":135.549713},{"店舗名":"【クレープ】プレミアムチェリッシュ 正雀店","住所":"〒566-0024 大阪府摂津市正雀本町１丁目１−３１","ステータス":"APP_DISPLAY","region":"Settsu","lat":34.775806,"lng":135.549713},{"店舗名":"AGRIM 正雀店 AGRIM Shojakuten","住所":"〒566-0024 大阪府摂津市正雀本町１丁目３３－８","ステータス":"APP_DISPLAY","region":"Settsu","lat":34.776218,"lng":135.546768},{"店舗名":"おいで舞","住所":"〒566-0024 大阪府摂津市正雀本町１丁目４０−１７","ステータス":"APP_DISPLAY","region":"Settsu","lat":34.777023,"lng":135.547134},{"店舗名":"居酒屋　蓮","住所":"〒566-0024 大阪府摂津市正雀本町1丁目40-2","ステータス":"APP_DISPLAY","region":"Settsu","lat":34.778175,"lng":135.547974},{"店舗名":"吉野家 中環学園町店","住所":"〒566-0033 大阪府摂津市学園町１丁目７−４４","ステータス":"APP_DISPLAY","region":"Settsu","lat":34.786514,"lng":135.562836},{"店舗名":"お出汁とおにぎりUMAMIYA","住所":"〒566-0034","ステータス":"APP_DISPLAY","region":"Settsu","lat":34.786709,"lng":135.556107},{"店舗名":"マヤ・キッチン Maya Kitchen","住所":"〒566-0034 大阪府摂津市香露園１−３０","ステータス":"APP_DISPLAY","region":"Settsu","lat":34.787125,"lng":135.554733},{"店舗名":"吉野家 摂津別府店","住所":"〒566-0042 大阪府摂津市東別府３丁目６−１２","ステータス":"APP_DISPLAY","region":"Settsu","lat":34.764618,"lng":135.560135},{"店舗名":"ケンタッキーフライドチキン 摂津東別府店","住所":"〒566-0042 大阪府摂津市東別府３丁目８−１１","ステータス":"APP_DISPLAY","region":"Settsu","lat":34.763374,"lng":135.557556},{"店舗名":"BombayKitchen","住所":"〒566-0043 大阪府摂津市一津屋３丁目４−１５","ステータス":"APP_DISPLAY","region":"Settsu","lat":34.76556,"lng":135.562332},{"店舗名":"ニク×ト×ソバ 本店","住所":"〒566-0046","ステータス":"APP_DISPLAY","region":"Settsu","lat":34.755749,"lng":135.554199},{"店舗名":"【出汁の旨みとたっぷり具材】雑炊の気分 摂津店","住所":"〒566-0046 大阪府摂津市別府","ステータス":"APP_DISPLAY","region":"Settsu","lat":34.755749,"lng":135.554199},{"店舗名":"dragon純豆腐(スンドゥブ) 東淀川店","住所":"〒566-0046 大阪府摂津市別府１丁目１５−５４","ステータス":"APP_DISPLAY","region":"Settsu","lat":34.765743,"lng":135.555023},{"店舗名":"ふわとろオムライスの店 東淀川たまごけん","住所":"〒566-0046 大阪府摂津市別府１丁目１５−５４","ステータス":"APP_DISPLAY","region":"Settsu","lat":34.765743,"lng":135.555023},{"店舗名":"ほっかほっか亭 鳥飼本町店","住所":"〒566-0052 大阪府摂津市鳥飼本町５丁目１６−３７","ステータス":"APP_DISPLAY","region":"Settsu","lat":34.773136,"lng":135.577545},{"店舗名":"Indian Nepal Resturant Shila","住所":"〒566-0053 大阪府摂津市鳥飼野々１丁目３０−２","ステータス":"APP_DISPLAY","region":"Settsu","lat":34.772202,"lng":135.576462},{"店舗名":"バーガーキング 摂津鳥飼八防店","住所":"〒566-0054 大阪府摂津市鳥飼八防２丁目１０−５","ステータス":"APP_DISPLAY","region":"Settsu","lat":34.770611,"lng":135.572693},{"店舗名":"ドミノ・ピザ 摂津新在家店","住所":"〒566-0054 大阪府摂津市鳥飼八防２丁目１１−１","ステータス":"APP_DISPLAY","region":"Settsu","lat":34.769806,"lng":135.571091},{"店舗名":"AQUA","住所":"〒566-0062 大阪府摂津市鳥飼上3丁目5-18","ステータス":"APP_DISPLAY","region":"Settsu","lat":34.78804,"lng":135.592194},{"店舗名":"吉野家 摂津鳥飼店","住所":"〒566-0062 大阪府摂津市鳥飼上４丁目１−３８","ステータス":"APP_DISPLAY","region":"Settsu","lat":34.789349,"lng":135.596268},{"店舗名":"cafe sith","住所":"〒566-0063","ステータス":"APP_DISPLAY","region":"Settsu","lat":34.78479,"lng":135.593643},{"店舗名":"串三六","住所":"〒566-0064 大阪府摂津市鳥飼中１丁目４−１","ステータス":"RECEIPT","region":"Settsu","lat":34.781315,"lng":135.592316},{"店舗名":"串三六","住所":"〒566-0064 大阪府摂津市鳥飼中１丁目４−１","ステータス":"APP_DISPLAY","region":"Settsu","lat":34.781315,"lng":135.592316},{"店舗名":"居酒屋カラオケBAR大心","住所":"〒566-0072","ステータス":"RECEIPT","region":"Settsu","lat":34.768875,"lng":135.582443},{"店舗名":"ふわふわ焼 智","住所":"摂津市正雀本町1丁目20-5","ステータス":"RECEIPT","region":"Settsu","lat":34.775623,"lng":135.549225}]